btchip/__init__.py
btchip/bitcoinTransaction.py
btchip/bitcoinVarint.py
btchip/btchip.py
btchip/btchipComm.py
btchip/btchipException.py
btchip/btchipFirmwareWizard.py
btchip/btchipHelpers.py
btchip/btchipKeyRecovery.py
btchip/btchipPersoWizard.py
btchip/btchipUtils.py
btchip/ledgerWrapper.py
btchip/msqr.py
btchip/ui/__init__.py
btchip/ui/personalization00start.py
btchip/ui/personalization01seed.py
btchip/ui/personalization02security.py
btchip/ui/personalization03config.py
btchip/ui/personalization04finalize.py
btchip/ui/personalizationseedbackup01.py
btchip/ui/personalizationseedbackup02.py
btchip/ui/personalizationseedbackup03.py
btchip/ui/personalizationseedbackup04.py
electrumsv_btchip_python-0.1.32.dist-info/LICENSE
electrumsv_btchip_python-0.1.32.dist-info/METADATA
electrumsv_btchip_python-0.1.32.dist-info/WHEEL
electrumsv_btchip_python-0.1.32.dist-info/top_level.txt
electrumsv_btchip_python-0.1.32.dist-info/RECORD
