Metadata-Version: 2.1
Name: electrumsv-btchip-python
Version: 0.1.32
Summary: Python library to communicate with Ledger Nano dongle
Home-page: https://github.com/electrumsv/btchip-python
Author: ElectrumSV developers
Author-email: roger.taylor.email@gmail.com
Classifier: License :: OSI Approved :: Apache Software License
Classifier: Operating System :: POSIX :: Linux
Classifier: Operating System :: Microsoft :: Windows
Classifier: Operating System :: MacOS :: MacOS X
License-File: LICENSE
Requires-Dist: hidapi (>=0.7.99)
Requires-Dist: ecdsa (>=0.9)
